sciluigi/__init__.py
sciluigi/audit.py
sciluigi/dependencies.py
sciluigi/interface.py
sciluigi/parameter.py
sciluigi/slurm.py
sciluigi/task.py
sciluigi/util.py
sciluigi/workflow.py
sciluigi-0.10.1.dist-info/LICENSE
sciluigi-0.10.1.dist-info/METADATA
sciluigi-0.10.1.dist-info/WHEEL
sciluigi-0.10.1.dist-info/top_level.txt
sciluigi-0.10.1.dist-info/RECORD
